ben_future_value/__init__.py
ben_future_value/future_value.py
ben_future_value-1.0.1.dist-info/LICENSE
ben_future_value-1.0.1.dist-info/METADATA
ben_future_value-1.0.1.dist-info/WHEEL
ben_future_value-1.0.1.dist-info/top_level.txt
ben_future_value-1.0.1.dist-info/RECORD
