Metadata-Version: 2.1
Name: ben_future_value
Version: 1.0.1
Summary: A package to assist in calculating future value
Author: Ben Payton
Project-URL: Documentation, https://github.com/Ben-Payton/ben_future_value/blob/main/README.md
Project-URL: Source, https://github.com/Ben-Payton/ben_future_value
License-File: LICENSE
Requires-Dist: matplotlib
Requires-Dist: seaborn
